Metadata-Version: 2.1
Name: plotID
Version: 0.3.2
Summary: The plotID toolkit supports researchers in tracking and storing relevant data in plots. Plots are labelled with an ID and the corresponding data is stored.
Author-email: Institut für Fluidsystemtechnik - TU Darmstadt <nfdi4ing@fst.tu-darmstadt.de>, Hannes Mayr <hannes.mayr@stud.tu-darmstadt.de>, Martin Hock <Martin.Hock@fst.tu-darmstadt.de>, Manuela Richter <Manuela.Richter@fst.tu-darmstadt.de>
License: Apache License, Version 2.0
Project-URL: Repository, https://git.rwth-aachen.de/plotid/plotid_python
Project-URL: Documentation, https://plotid.pages.rwth-aachen.de/plotid_python
Project-URL: Bug Tracker, https://git.rwth-aachen.de/plotid/plotid_python/-/issues
Classifier: Programming Language :: Python
Classifier: Programming Language :: Python :: 3 :: Only
Classifier: Programming Language :: Python :: 3.10
Classifier: License :: OSI Approved :: Apache Software License
Classifier: Operating System :: OS Independent
Classifier: Development Status :: 3 - Alpha
Classifier: Intended Audience :: Science/Research
Classifier: Topic :: Scientific/Engineering :: Visualization
Requires-Python: >=3.10
License-File: LICENSE
Requires-Dist: Pillow
Requires-Dist: matplotlib
Requires-Dist: numpy
Requires-Dist: qrcode
Provides-Extra: docs
Requires-Dist: sphinx ; extra == 'docs'
Requires-Dist: sphinx-autoapi ; extra == 'docs'
Requires-Dist: sphinx-rtd-theme ; extra == 'docs'
Requires-Dist: myst-parser ; extra == 'docs'
Provides-Extra: test
Requires-Dist: coverage ; extra == 'test'
